NEMbox/__init__.py
NEMbox/__main__.py
NEMbox/api.py
NEMbox/cache.py
NEMbox/cmd_parser.py
NEMbox/config.py
NEMbox/const.py
NEMbox/encrypt.py
NEMbox/kill_thread.py
NEMbox/logger.py
NEMbox/menu.py
NEMbox/osdlyrics.py
NEMbox/player.py
NEMbox/scrollstring.py
NEMbox/singleton.py
NEMbox/storage.py
NEMbox/ui.py
NEMbox/utils.py
netease_musicbox-0.3.1.dist-info/entry_points.txt
netease_musicbox-0.3.1.dist-info/LICENSE
netease_musicbox-0.3.1.dist-info/WHEEL
netease_musicbox-0.3.1.dist-info/METADATA
netease_musicbox-0.3.1.dist-info/RECORD
