Metadata-Version: 2.1
Name: netease-musicbox
Version: 0.3.1
Summary: A sexy command line interface musicbox
Home-page: https://github.com/darknessomi/musicbox
License: MIT
Keywords: music,netease,cli,player
Author: omi
Author-email: 4399.omi@gmail.com
Maintainer: omi
Maintainer-email: 4399.omi@gmail.com
Requires-Python: >=3.6,<4.0
Classifier: Development Status :: 4 - Beta
Classifier: Intended Audience :: Developers
Classifier: License :: OSI Approved :: MIT License
Classifier: Natural Language :: Chinese (Simplified)
Classifier: Operating System :: OS Independent
Classifier: Programming Language :: Python :: 3
Classifier: Programming Language :: Python :: 3.6
Classifier: Programming Language :: Python :: 3.7
Classifier: Programming Language :: Python :: 3.8
Classifier: Programming Language :: Python :: 3.9
Classifier: Programming Language :: Python :: Implementation :: CPython
Classifier: Topic :: Multimedia :: Sound/Audio
Requires-Dist: fuzzywuzzy (>=0.18.0,<0.19.0)
Requires-Dist: importlib-metadata (>=2.0.0,<3.0.0)
Requires-Dist: pycryptodomex (>=3.9.8,<4.0.0)
Requires-Dist: python-Levenshtein (>=0.12.0,<0.13.0)
Requires-Dist: requests (>=2.24.0,<3.0.0)
Requires-Dist: requests-cache (>=0.5.2,<0.6.0)
Project-URL: Repository, https://github.com/darknessomi/musicbox
